gpp_cracker/__init__.py
gpp_cracker/cli.py
gpp_cracker-1.0.dist-info/METADATA
gpp_cracker-1.0.dist-info/WHEEL
gpp_cracker-1.0.dist-info/entry_points.txt
gpp_cracker-1.0.dist-info/top_level.txt
gpp_cracker-1.0.dist-info/RECORD
